constraintula/__init__.py
constraintula/core.py
constraintula-0.3.1.dist-info/AUTHORS
constraintula-0.3.1.dist-info/LICENSE
constraintula-0.3.1.dist-info/METADATA
constraintula-0.3.1.dist-info/WHEEL
constraintula-0.3.1.dist-info/top_level.txt
constraintula-0.3.1.dist-info/RECORD
