Metadata-Version: 2.1
Name: constraintula
Version: 0.3.1
Summary: Define system of constraint equations for initializing data classes
Home-page: https://github.com/DanielSank/constraintula
Author: Daniel Sank
Author-email: sank.daniel@gmail.com
License: UNKNOWN
Platform: UNKNOWN
Classifier: Programming Language :: Python :: 3
Classifier: Operating System :: OS Independent
License-File: LICENSE
License-File: AUTHORS
Requires-Dist: numpy
Requires-Dist: sympy
Requires-Dist: typing ; python_version < "3.5.0"
Provides-Extra: dev
Requires-Dist: attrs ; extra == 'dev'
Requires-Dist: pytest ; extra == 'dev'
